pretix_hide_sold_out/__init__.py
pretix_hide_sold_out/apps.py
pretix_hide_sold_out/locale/de/LC_MESSAGES/django.mo
pretix_hide_sold_out/locale/de/LC_MESSAGES/django.po
pretix_hide_sold_out/locale/de_Informal/.gitkeep
pretix_hide_sold_out/locale/de_Informal/LC_MESSAGES/django.mo
pretix_hide_sold_out/locale/de_Informal/LC_MESSAGES/django.po
pretix_hide_sold_out/management/__init__.py
pretix_hide_sold_out/management/commands/__init__.py
pretix_hide_sold_out/management/commands/hide_sold_out.py
pretix_hide_sold_out/static/pretix_hide_sold_out/.gitkeep
pretix_hide_sold_out/templates/pretix_hide_sold_out/.gitkeep
pretix_hide_sold_out-1.1.0.dist-info/LICENSE
pretix_hide_sold_out-1.1.0.dist-info/METADATA
pretix_hide_sold_out-1.1.0.dist-info/WHEEL
pretix_hide_sold_out-1.1.0.dist-info/entry_points.txt
pretix_hide_sold_out-1.1.0.dist-info/top_level.txt
pretix_hide_sold_out-1.1.0.dist-info/RECORD
