Metadata-Version: 2.1
Name: pretix-hide-sold-out
Version: 1.1.0
Summary: Hide sold out events
Home-page: https://github.com/pretix-unofficial/pretix-hide-sold-out
Author: pretix team
Author-email: support@pretix.eu
License: Apache
License-File: LICENSE
